pytest_kafkavents.py
pytest_kafkavents-0.2.2.1.dist-info/LICENSE
pytest_kafkavents-0.2.2.1.dist-info/METADATA
pytest_kafkavents-0.2.2.1.dist-info/WHEEL
pytest_kafkavents-0.2.2.1.dist-info/entry_points.txt
pytest_kafkavents-0.2.2.1.dist-info/top_level.txt
pytest_kafkavents-0.2.2.1.dist-info/RECORD
